box/__init__.py
box/box.py
box/box.pyi
box/box_list.py
box/box_list.pyi
box/config_box.py
box/config_box.pyi
box/converters.py
box/converters.pyi
box/exceptions.py
box/exceptions.pyi
box/from_file.py
box/from_file.pyi
box/py.typed
box/shorthand_box.py
box/shorthand_box.pyi
python_box-7.3.2.dist-info/AUTHORS.rst
python_box-7.3.2.dist-info/LICENSE
python_box-7.3.2.dist-info/METADATA
python_box-7.3.2.dist-info/WHEEL
python_box-7.3.2.dist-info/top_level.txt
python_box-7.3.2.dist-info/RECORD
