Metadata-Version: 2.2
Name: python-box
Version: 7.3.2
Summary: Advanced Python dictionaries with dot notation access
Home-page: https://github.com/cdgriffith/Box
Author: Chris Griffith
Author-email: chris@cdgriffith.com
License: MIT
Platform: any
Classifier: Programming Language :: Python
Classifier: Programming Language :: Python :: 3
Classifier: Programming Language :: Python :: 3.9
Classifier: Programming Language :: Python :: 3.10
Classifier: Programming Language :: Python :: 3.11
Classifier: Programming Language :: Python :: 3.12
Classifier: Programming Language :: Python :: 3.13
Classifier: Programming Language :: Python :: Implementation :: CPython
Classifier: Development Status :: 5 - Production/Stable
Classifier: Natural Language :: English
Classifier: Intended Audience :: Developers
Classifier: License :: OSI Approved :: MIT License
Classifier: Operating System :: OS Independent
Classifier: Topic :: Utilities
Classifier: Topic :: Software Development
Classifier: Topic :: Software Development :: Libraries :: Python Modules
Requires-Python: >=3.9
License-File: LICENSE
License-File: AUTHORS.rst
Provides-Extra: all
Requires-Dist: ruamel.yaml>=0.17; extra == "all"
Requires-Dist: toml; extra == "all"
Requires-Dist: msgpack; extra == "all"
Provides-Extra: yaml
Requires-Dist: ruamel.yaml>=0.17; extra == "yaml"
Provides-Extra: ruamel-yaml
Requires-Dist: ruamel.yaml>=0.17; extra == "ruamel-yaml"
Provides-Extra: pyyaml
Requires-Dist: PyYAML; extra == "pyyaml"
Provides-Extra: tomli
Requires-Dist: tomli; python_version < "3.11" and extra == "tomli"
Requires-Dist: tomli-w; extra == "tomli"
Provides-Extra: toml
Requires-Dist: toml; extra == "toml"
Provides-Extra: msgpack
Requires-Dist: msgpack; extra == "msgpack"
Dynamic: author
Dynamic: author-email
Dynamic: classifier
Dynamic: description
Dynamic: description-content-type
Dynamic: home-page
Dynamic: license
Dynamic: platform
Dynamic: provides-extra
Dynamic: requires-python
Dynamic: summary
